finbr/__init__.py
finbr/_yf.py
finbr/b3/__init__.py
finbr/b3/cotahist.py
finbr/b3/di1.py
finbr/b3/indices.py
finbr/b3/plantao_noticias.py
finbr/b3/utils.py
finbr/backtest/__init__.py
finbr/dias_uteis/__init__.py
finbr/dias_uteis/base.py
finbr/dias_uteis/feriados.py
finbr/fundamentus/__init__.py
finbr/sgs/__init__.py
finbr/statusinvest/__init__.py
finbr/statusinvest/_utils.py
finbr/statusinvest/acao.py
finbr-0.2.3.dist-info/LICENSE
finbr-0.2.3.dist-info/METADATA
finbr-0.2.3.dist-info/WHEEL
finbr-0.2.3.dist-info/RECORD
