Metadata-Version: 2.3
Name: finbr
Version: 0.2.3
Summary: Coleção de utilitários Python para o mercado financeiro brasileiro.
Author: Renan Moretto
Author-email: renan_moretto@outlook.com
Requires-Python: >=3.10
Classifier: Programming Language :: Python :: 3
Classifier: Programming Language :: Python :: 3.10
Classifier: Programming Language :: Python :: 3.11
Classifier: Programming Language :: Python :: 3.12
Classifier: Programming Language :: Python :: 3.13
Requires-Dist: pandas (>=2.2.0,<3.0.0)
Requires-Dist: polars (>=1.20.0,<2.0.0)
Requires-Dist: pyarrow (>=19.0.0,<20.0.0)
Requires-Dist: requests (>=2.30.0,<3.0.0)
Requires-Dist: unidecode (>=1.3.8,<2.0.0)
Requires-Dist: yfinance (>=0.2.54,<0.3.0)
